pyautomation/__init__.py
pyautomation/controller.py
pyautomation/modules.py
pyautomation/utils.py
PyAutomation-0.0.1.dist-info/LICENSE
PyAutomation-0.0.1.dist-info/METADATA
PyAutomation-0.0.1.dist-info/WHEEL
PyAutomation-0.0.1.dist-info/top_level.txt
PyAutomation-0.0.1.dist-info/RECORD
