Metadata-Version: 2.1
Name: PyAutomation
Version: 0.0.1
Summary: A python library used to interface with the Aerotech automation1 controller API.
Author-email: Christofanis Skordas <55315750+skordaschristofanis@users.noreply.github.com>, Stella Chariton <52049100+CharitonS@users.noreply.github.com>
Maintainer-email: Christofanis Skordas <55315750+skordaschristofanis@users.noreply.github.com>
License: MIT License
Project-URL: Homepage, https://github.com/GSECARS/PyAutomation
Project-URL: Issues, https://github.com/GSECARS/PyAutomation/issues
Classifier: Intended Audience :: Science/Research
Classifier: Operating System :: OS Independent
Classifier: Programming Language :: Python :: 3
Classifier: Programming Language :: Python :: 3 :: Only
Classifier: Programming Language :: Python :: 3.12
Classifier: License :: OSI Approved :: MIT License
Classifier: Topic :: Scientific/Engineering
Requires-Python: >=3.12
License-File: LICENSE
Provides-Extra: development
Requires-Dist: black>=24.8.0; extra == "development"
Requires-Dist: flake8>=7.1.1; extra == "development"
Requires-Dist: mypy>=1.11.2; extra == "development"
Requires-Dist: pre-commit>=3.8.0; extra == "development"
Requires-Dist: setuptools>=75.1.0; extra == "development"
Requires-Dist: setuptools-scm>=8.1.0; extra == "development"
Requires-Dist: twine>=5.1.1; extra == "development"
